axiom
sympy
util
