Metadata-Version: 1.1
Name: axiom.top
Version: 1.0.0
Summary: UNKNOWN
Home-page: https://github.com/cosmosZhou/sympy
Author: Cosmos
Author-email: 744984949@qq.com
License: MIT
Platform: UNKNOWN
Classifier: Programming Language :: Python :: 3.9
